telemetry_wire/__init__.py
telemetry_wire/wire.py
telemetry_wire-0.1.0.dist-info/WHEEL
telemetry_wire-0.1.0.dist-info/METADATA
telemetry_wire-0.1.0.dist-info/RECORD
