Metadata-Version: 2.1
Name: telemetry-wire
Version: 0.1.0
Summary: An SDK for accessing Telemetry Wire
Author: Chris Moyer
Author-email: chris@telemetry.fm
Requires-Python: >=3.8,<4.0
Classifier: Programming Language :: Python :: 3
Classifier: Programming Language :: Python :: 3.8
Classifier: Programming Language :: Python :: 3.9
Classifier: Programming Language :: Python :: 3.10
Classifier: Programming Language :: Python :: 3.11
Requires-Dist: requests (>=2.28.2,<3.0.0)
